pyverno.py
pyverno-1.0.0.dist-info/METADATA
pyverno-1.0.0.dist-info/WHEEL
pyverno-1.0.0.dist-info/entry_points.txt
pyverno-1.0.0.dist-info/licenses/LICENSE
pyverno-1.0.0.dist-info/RECORD
