Metadata-Version: 2.4
Name: pyverno
Version: 1.0.0
Summary: Python package version checker/updater
Project-URL: Home, https://github.com/dimagi/pyverno
Author-email: Daniel Miller <millerdev@gmail.com>
License: Copyright (c) 2025, Dimagi Inc., and individual contributors.
License-File: LICENSE
Classifier: Development Status :: 5 - Production/Stable
Classifier: Intended Audience :: Developers
Classifier: License :: OSI Approved :: BSD License
Classifier: Operating System :: OS Independent
Classifier: Programming Language :: Python
Classifier: Programming Language :: Python :: 3
Classifier: Programming Language :: Python :: 3.9
Classifier: Programming Language :: Python :: 3.10
Classifier: Programming Language :: Python :: 3.11
Classifier: Programming Language :: Python :: 3.12
Classifier: Programming Language :: Python :: 3.13
Classifier: Programming Language :: Python :: 3.14
Classifier: Topic :: Software Development :: Libraries :: Python Modules
Requires-Python: >=3.9
